ticker_to_searchable_terms/.DS_Store
ticker_to_searchable_terms/__init__.py
ticker_to_searchable_terms/database_management.py
ticker_to_searchable_terms-0.13.dist-info/WHEEL
ticker_to_searchable_terms-0.13.dist-info/METADATA
ticker_to_searchable_terms-0.13.dist-info/RECORD
