Metadata-Version: 2.1
Name: ticker-to-searchable-terms
Version: 0.13
Summary: Generate searchable terms for public companies based off of the ticker.
Home-page: https://github.com/BecketTrotter/ticker_terms
License: MIT
Keywords: stock,ticker,ceo,executives,seo
Author: Henry Becket Trotter
Author-email: beckettrotter@gmail.com
Requires-Python: >=3.6,<4.0
Classifier: Environment :: Console
Classifier: License :: OSI Approved :: MIT License
Classifier: Operating System :: OS Independent
Classifier: Programming Language :: Python :: 3
Classifier: Programming Language :: Python :: 3.6
Classifier: Programming Language :: Python :: 3.7
Classifier: Programming Language :: Python :: 3.8
Classifier: Topic :: Software Development :: Documentation
Classifier: Topic :: Software Development :: Libraries :: Python Modules
Project-URL: Repository, https://github.com/BecketTrotter/ticker_terms
